{
    "@context": [
        "http://iiif.io/api/presentation/2/context.json",
        "http://codh.rois.ac.jp/iiif/curation/1/context.json"
    ],
    "@id": "https://nakamura196.github.io/gaikotsu-i/curation/27674e299e8c72e68409902269b63727.json",
    "@type": "cr:Curation",
    "label": "Curating list",
    "selections": [
        {
            "@id": "https://nakamura196.github.io/gaikotsu-i/curation/27674e299e8c72e68409902269b63727.json/range1",
            "@type": "sc:Range",
            "label": "Manual curation by IIIF Curation Viewer",
            "members": [
                {
                    "@id": "https://iiif.dl.itc.u-tokyo.ac.jp/repo/iiif/dbbf40af-d39e-4339-bb10-2b3ebce97851/canvas/p3#xywh=56,556,6121,3460",
                    "@type": "sc:Canvas",
                    "label": "[1]",
                    "metadata": [
                        {
                            "label": "Score",
                            "value": 0
                        }
                    ],
                    "thumbnail": "https://iiif.dl.itc.u-tokyo.ac.jp/repo/iiif-img/87875/56,556,6121,3460/,300/0/default.jpg"
                },
                {
                    "@id": "https://iiif.dl.itc.u-tokyo.ac.jp/repo/iiif/dbbf40af-d39e-4339-bb10-2b3ebce97851/canvas/p4#xywh=282,443,6960,3895",
                    "@type": "sc:Canvas",
                    "label": "[2]",
                    "metadata": [
                        {
                            "label": "Score",
                            "value": 0
                        }
                    ],
                    "thumbnail": "https://iiif.dl.itc.u-tokyo.ac.jp/repo/iiif-img/87876/282,443,6960,3895/,300/0/default.jpg"
                },
                {
                    "@id": "https://iiif.dl.itc.u-tokyo.ac.jp/repo/iiif/dbbf40af-d39e-4339-bb10-2b3ebce97851/canvas/p5#xywh=3165,809,1668,3371",
                    "@type": "sc:Canvas",
                    "label": "[3]",
                    "metadata": [
                        {
                            "label": "Score",
                            "value": 0
                        }
                    ],
                    "thumbnail": "https://iiif.dl.itc.u-tokyo.ac.jp/repo/iiif-img/87877/3165,809,1668,3371/,300/0/default.jpg"
                },
                {
                    "@id": "https://iiif.dl.itc.u-tokyo.ac.jp/repo/iiif/dbbf40af-d39e-4339-bb10-2b3ebce97851/canvas/p5#xywh=1389,652,1897,5969",
                    "@type": "sc:Canvas",
                    "label": "[4]",
                    "metadata": [
                        {
                            "label": "Score",
                            "value": 0
                        }
                    ],
                    "thumbnail": "https://iiif.dl.itc.u-tokyo.ac.jp/repo/iiif-img/87877/1389,652,1897,5969/,300/0/default.jpg"
                },
                {
                    "@id": "https://iiif.dl.itc.u-tokyo.ac.jp/repo/iiif/dbbf40af-d39e-4339-bb10-2b3ebce97851/canvas/p6#xywh=0,435,6766,3855",
                    "@type": "sc:Canvas",
                    "label": "[5]",
                    "metadata": [
                        {
                            "label": "Score",
                            "value": 0
                        }
                    ],
                    "thumbnail": "https://iiif.dl.itc.u-tokyo.ac.jp/repo/iiif-img/87878/0,435,6766,3855/,300/0/default.jpg"
                },
                {
                    "@id": "https://iiif.dl.itc.u-tokyo.ac.jp/repo/iiif/dbbf40af-d39e-4339-bb10-2b3ebce97851/canvas/p8#xywh=2387,532,2242,3936",
                    "@type": "sc:Canvas",
                    "label": "[6]",
                    "metadata": [
                        {
                            "label": "Score",
                            "value": 0
                        }
                    ],
                    "thumbnail": "https://iiif.dl.itc.u-tokyo.ac.jp/repo/iiif-img/87880/2387,532,2242,3936/,300/0/default.jpg"
                },
                {
                    "@id": "https://iiif.dl.itc.u-tokyo.ac.jp/repo/iiif/dbbf40af-d39e-4339-bb10-2b3ebce97851/canvas/p9#xywh=250,483,6629,3920",
                    "@type": "sc:Canvas",
                    "label": "[7]",
                    "metadata": [
                        {
                            "label": "Score",
                            "value": 0
                        }
                    ],
                    "thumbnail": "https://iiif.dl.itc.u-tokyo.ac.jp/repo/iiif-img/87881/250,483,6629,3920/,300/0/default.jpg"
                },
                {
                    "@id": "https://iiif.dl.itc.u-tokyo.ac.jp/repo/iiif/dbbf40af-d39e-4339-bb10-2b3ebce97851/canvas/p12#xywh=540,653,6702,3685",
                    "@type": "sc:Canvas",
                    "label": "[8]",
                    "metadata": [
                        {
                            "label": "Score",
                            "value": 0
                        }
                    ],
                    "thumbnail": "https://iiif.dl.itc.u-tokyo.ac.jp/repo/iiif-img/87884/540,653,6702,3685/,300/0/default.jpg"
                },
                {
                    "@id": "https://iiif.dl.itc.u-tokyo.ac.jp/repo/iiif/dbbf40af-d39e-4339-bb10-2b3ebce97851/canvas/p13#xywh=2459,596,1984,3597",
                    "@type": "sc:Canvas",
                    "label": "[9]",
                    "metadata": [
                        {
                            "label": "Score",
                            "value": 0
                        }
                    ],
                    "thumbnail": "https://iiif.dl.itc.u-tokyo.ac.jp/repo/iiif-img/87885/2459,596,1984,3597/,300/0/default.jpg"
                },
                {
                    "@id": "https://iiif.dl.itc.u-tokyo.ac.jp/repo/iiif/dbbf40af-d39e-4339-bb10-2b3ebce97851/canvas/p14#xywh=64,500,7025,4080",
                    "@type": "sc:Canvas",
                    "label": "[10]",
                    "metadata": [
                        {
                            "label": "Score",
                            "value": 0
                        }
                    ],
                    "thumbnail": "https://iiif.dl.itc.u-tokyo.ac.jp/repo/iiif-img/87886/64,500,7025,4080/,300/0/default.jpg"
                },
                {
                    "@id": "https://iiif.dl.itc.u-tokyo.ac.jp/repo/iiif/dbbf40af-d39e-4339-bb10-2b3ebce97851/canvas/p15#xywh=653,540,6331,3944",
                    "@type": "sc:Canvas",
                    "label": "[11]",
                    "metadata": [
                        {
                            "label": "Score",
                            "value": 0
                        }
                    ],
                    "thumbnail": "https://iiif.dl.itc.u-tokyo.ac.jp/repo/iiif-img/87887/653,540,6331,3944/,300/0/default.jpg"
                },
                {
                    "@id": "https://iiif.dl.itc.u-tokyo.ac.jp/repo/iiif/dbbf40af-d39e-4339-bb10-2b3ebce97851/canvas/p16#xywh=2967,806,1089,1782",
                    "@type": "sc:Canvas",
                    "label": "[12]",
                    "metadata": [
                        {
                            "label": "Score",
                            "value": 0
                        }
                    ],
                    "thumbnail": "https://iiif.dl.itc.u-tokyo.ac.jp/repo/iiif-img/87888/2967,806,1089,1782/,300/0/default.jpg"
                },
                {
                    "@id": "https://iiif.dl.itc.u-tokyo.ac.jp/repo/iiif/dbbf40af-d39e-4339-bb10-2b3ebce97851/canvas/p18#xywh=241,822,5581,3283",
                    "@type": "sc:Canvas",
                    "label": "[13]",
                    "metadata": [
                        {
                            "label": "Score",
                            "value": 0
                        }
                    ],
                    "thumbnail": "https://iiif.dl.itc.u-tokyo.ac.jp/repo/iiif-img/87890/241,822,5581,3283/,300/0/default.jpg"
                },
                {
                    "@id": "https://iiif.dl.itc.u-tokyo.ac.jp/repo/iiif/dbbf40af-d39e-4339-bb10-2b3ebce97851/canvas/p19#xywh=1121,701,6121,3646",
                    "@type": "sc:Canvas",
                    "label": "[14]",
                    "metadata": [
                        {
                            "label": "Score",
                            "value": 0
                        }
                    ],
                    "thumbnail": "https://iiif.dl.itc.u-tokyo.ac.jp/repo/iiif-img/87891/1121,701,6121,3646/,300/0/default.jpg"
                },
                {
                    "@id": "https://iiif.dl.itc.u-tokyo.ac.jp/repo/iiif/dbbf40af-d39e-4339-bb10-2b3ebce97851/canvas/p20#xywh=2137,895,2597,3218",
                    "@type": "sc:Canvas",
                    "label": "[15]",
                    "metadata": [
                        {
                            "label": "Score",
                            "value": 0
                        }
                    ],
                    "thumbnail": "https://iiif.dl.itc.u-tokyo.ac.jp/repo/iiif-img/87892/2137,895,2597,3218/,300/0/default.jpg"
                },
                {
                    "@id": "https://iiif.dl.itc.u-tokyo.ac.jp/repo/iiif/dbbf40af-d39e-4339-bb10-2b3ebce97851/canvas/p21#xywh=88,750,6952,3709",
                    "@type": "sc:Canvas",
                    "label": "[16]",
                    "metadata": [
                        {
                            "label": "Score",
                            "value": 0
                        }
                    ],
                    "thumbnail": "https://iiif.dl.itc.u-tokyo.ac.jp/repo/iiif-img/87893/88,750,6952,3709/,300/0/default.jpg"
                },
                {
                    "@id": "https://iiif.dl.itc.u-tokyo.ac.jp/repo/iiif/dbbf40af-d39e-4339-bb10-2b3ebce97851/canvas/p23#xywh=0,1209,5032,2420",
                    "@type": "sc:Canvas",
                    "label": "[17]",
                    "metadata": [
                        {
                            "label": "Score",
                            "value": 0
                        }
                    ],
                    "thumbnail": "https://iiif.dl.itc.u-tokyo.ac.jp/repo/iiif-img/87895/0,1209,5032,2420/,300/0/default.jpg"
                },
                {
                    "@id": "https://iiif.dl.itc.u-tokyo.ac.jp/repo/iiif/dbbf40af-d39e-4339-bb10-2b3ebce97851/canvas/p23#xywh=0,580,7242,3952",
                    "@type": "sc:Canvas",
                    "label": "[18]",
                    "metadata": [
                        {
                            "label": "Score",
                            "value": 0
                        }
                    ],
                    "thumbnail": "https://iiif.dl.itc.u-tokyo.ac.jp/repo/iiif-img/87895/0,580,7242,3952/,300/0/default.jpg"
                },
                {
                    "@id": "https://iiif.dl.itc.u-tokyo.ac.jp/repo/iiif/dbbf40af-d39e-4339-bb10-2b3ebce97851/canvas/p24#xywh=580,685,6420,3581",
                    "@type": "sc:Canvas",
                    "label": "[19]",
                    "metadata": [
                        {
                            "label": "Score",
                            "value": 0
                        }
                    ],
                    "thumbnail": "https://iiif.dl.itc.u-tokyo.ac.jp/repo/iiif-img/87896/580,685,6420,3581/,300/0/default.jpg"
                },
                {
                    "@id": "https://iiif.dl.itc.u-tokyo.ac.jp/repo/iiif/dbbf40af-d39e-4339-bb10-2b3ebce97851/canvas/p26#xywh=48,717,7194,3630",
                    "@type": "sc:Canvas",
                    "label": "[20]",
                    "metadata": [
                        {
                            "label": "Score",
                            "value": 0
                        }
                    ],
                    "thumbnail": "https://iiif.dl.itc.u-tokyo.ac.jp/repo/iiif-img/87898/48,717,7194,3630/,300/0/default.jpg"
                },
                {
                    "@id": "https://iiif.dl.itc.u-tokyo.ac.jp/repo/iiif/dbbf40af-d39e-4339-bb10-2b3ebce97851/canvas/p29#xywh=2459,467,2412,3928",
                    "@type": "sc:Canvas",
                    "label": "[21]",
                    "metadata": [
                        {
                            "label": "Score",
                            "value": 0
                        }
                    ],
                    "thumbnail": "https://iiif.dl.itc.u-tokyo.ac.jp/repo/iiif-img/87901/2459,467,2412,3928/,300/0/default.jpg"
                },
                {
                    "@id": "https://iiif.dl.itc.u-tokyo.ac.jp/repo/iiif/dbbf40af-d39e-4339-bb10-2b3ebce97851/canvas/p30#xywh=346,403,6299,3863",
                    "@type": "sc:Canvas",
                    "label": "[22]",
                    "metadata": [
                        {
                            "label": "Score",
                            "value": 0
                        }
                    ],
                    "thumbnail": "https://iiif.dl.itc.u-tokyo.ac.jp/repo/iiif-img/87902/346,403,6299,3863/,300/0/default.jpg"
                },
                {
                    "@id": "https://iiif.dl.itc.u-tokyo.ac.jp/repo/iiif/dbbf40af-d39e-4339-bb10-2b3ebce97851/canvas/p32#xywh=96,556,7146,3694",
                    "@type": "sc:Canvas",
                    "label": "[23]",
                    "metadata": [
                        {
                            "label": "Score",
                            "value": 0
                        }
                    ],
                    "thumbnail": "https://iiif.dl.itc.u-tokyo.ac.jp/repo/iiif-img/87904/96,556,7146,3694/,300/0/default.jpg"
                },
                {
                    "@id": "https://iiif.dl.itc.u-tokyo.ac.jp/repo/iiif/dbbf40af-d39e-4339-bb10-2b3ebce97851/canvas/p33#xywh=2330,758,1855,3548",
                    "@type": "sc:Canvas",
                    "label": "[24]",
                    "metadata": [
                        {
                            "label": "Score",
                            "value": 0
                        }
                    ],
                    "thumbnail": "https://iiif.dl.itc.u-tokyo.ac.jp/repo/iiif-img/87905/2330,758,1855,3548/,300/0/default.jpg"
                },
                {
                    "@id": "https://iiif.dl.itc.u-tokyo.ac.jp/repo/iiif/dbbf40af-d39e-4339-bb10-2b3ebce97851/canvas/p34#xywh=1298,1016,4895,2943",
                    "@type": "sc:Canvas",
                    "label": "[25]",
                    "metadata": [
                        {
                            "label": "Score",
                            "value": 0
                        }
                    ],
                    "thumbnail": "https://iiif.dl.itc.u-tokyo.ac.jp/repo/iiif-img/87906/1298,1016,4895,2943/,300/0/default.jpg"
                },
                {
                    "@id": "https://iiif.dl.itc.u-tokyo.ac.jp/repo/iiif/dbbf40af-d39e-4339-bb10-2b3ebce97851/canvas/p35#xywh=959,741,5355,3444",
                    "@type": "sc:Canvas",
                    "label": "[26]",
                    "metadata": [
                        {
                            "label": "Score",
                            "value": 0
                        }
                    ],
                    "thumbnail": "https://iiif.dl.itc.u-tokyo.ac.jp/repo/iiif-img/87907/959,741,5355,3444/,300/0/default.jpg"
                },
                {
                    "@id": "https://iiif.dl.itc.u-tokyo.ac.jp/repo/iiif/dbbf40af-d39e-4339-bb10-2b3ebce97851/canvas/p36#xywh=983,943,5009,3008",
                    "@type": "sc:Canvas",
                    "label": "[27]",
                    "metadata": [
                        {
                            "label": "Score",
                            "value": 0
                        }
                    ],
                    "thumbnail": "https://iiif.dl.itc.u-tokyo.ac.jp/repo/iiif-img/87908/983,943,5009,3008/,300/0/default.jpg"
                },
                {
                    "@id": "https://iiif.dl.itc.u-tokyo.ac.jp/repo/iiif/dbbf40af-d39e-4339-bb10-2b3ebce97851/canvas/p37#xywh=846,387,5493,3726",
                    "@type": "sc:Canvas",
                    "label": "[28]",
                    "metadata": [
                        {
                            "label": "Score",
                            "value": 0
                        }
                    ],
                    "thumbnail": "https://iiif.dl.itc.u-tokyo.ac.jp/repo/iiif-img/87909/846,387,5493,3726/,300/0/default.jpg"
                },
                {
                    "@id": "https://iiif.dl.itc.u-tokyo.ac.jp/repo/iiif/dbbf40af-d39e-4339-bb10-2b3ebce97851/canvas/p38#xywh=2161,379,2637,4072",
                    "@type": "sc:Canvas",
                    "label": "[29]",
                    "metadata": [
                        {
                            "label": "Score",
                            "value": 0
                        }
                    ],
                    "thumbnail": "https://iiif.dl.itc.u-tokyo.ac.jp/repo/iiif-img/87910/2161,379,2637,4072/,300/0/default.jpg"
                },
                {
                    "@id": "https://iiif.dl.itc.u-tokyo.ac.jp/repo/iiif/dbbf40af-d39e-4339-bb10-2b3ebce97851/canvas/p40#xywh=661,354,6581,4178",
                    "@type": "sc:Canvas",
                    "label": "[30]",
                    "metadata": [
                        {
                            "label": "Score",
                            "value": 0
                        }
                    ],
                    "thumbnail": "https://iiif.dl.itc.u-tokyo.ac.jp/repo/iiif-img/87912/661,354,6581,4178/,300/0/default.jpg"
                },
                {
                    "@id": "https://iiif.dl.itc.u-tokyo.ac.jp/repo/iiif/dbbf40af-d39e-4339-bb10-2b3ebce97851/canvas/p43#xywh=217,338,6646,4154",
                    "@type": "sc:Canvas",
                    "label": "[31]",
                    "metadata": [
                        {
                            "label": "Score",
                            "value": 0
                        }
                    ],
                    "thumbnail": "https://iiif.dl.itc.u-tokyo.ac.jp/repo/iiif-img/87915/217,338,6646,4154/,300/0/default.jpg"
                },
                {
                    "@id": "https://iiif.dl.itc.u-tokyo.ac.jp/repo/iiif/dbbf40af-d39e-4339-bb10-2b3ebce97851/canvas/p45#xywh=209,500,6638,3911",
                    "@type": "sc:Canvas",
                    "label": "[32]",
                    "metadata": [
                        {
                            "label": "Score",
                            "value": 0
                        }
                    ],
                    "thumbnail": "https://iiif.dl.itc.u-tokyo.ac.jp/repo/iiif-img/87917/209,500,6638,3911/,300/0/default.jpg"
                },
                {
                    "@id": "https://iiif.dl.itc.u-tokyo.ac.jp/repo/iiif/dbbf40af-d39e-4339-bb10-2b3ebce97851/canvas/p46#xywh=532,451,6565,3839",
                    "@type": "sc:Canvas",
                    "label": "[33]",
                    "metadata": [
                        {
                            "label": "Score",
                            "value": 0
                        }
                    ],
                    "thumbnail": "https://iiif.dl.itc.u-tokyo.ac.jp/repo/iiif-img/87918/532,451,6565,3839/,300/0/default.jpg"
                },
                {
                    "@id": "https://iiif.dl.itc.u-tokyo.ac.jp/repo/iiif/dbbf40af-d39e-4339-bb10-2b3ebce97851/canvas/p47#xywh=2403,685,2048,3395",
                    "@type": "sc:Canvas",
                    "label": "[34]",
                    "metadata": [
                        {
                            "label": "Score",
                            "value": 0
                        }
                    ],
                    "thumbnail": "https://iiif.dl.itc.u-tokyo.ac.jp/repo/iiif-img/87919/2403,685,2048,3395/,300/0/default.jpg"
                },
                {
                    "@id": "https://iiif.dl.itc.u-tokyo.ac.jp/repo/iiif/dbbf40af-d39e-4339-bb10-2b3ebce97851/canvas/p48#xywh=0,661,6935,3589",
                    "@type": "sc:Canvas",
                    "label": "[35]",
                    "metadata": [
                        {
                            "label": "Score",
                            "value": 0
                        }
                    ],
                    "thumbnail": "https://iiif.dl.itc.u-tokyo.ac.jp/repo/iiif-img/87920/0,661,6935,3589/,300/0/default.jpg"
                },
                {
                    "@id": "https://iiif.dl.itc.u-tokyo.ac.jp/repo/iiif/dbbf40af-d39e-4339-bb10-2b3ebce97851/canvas/p50#xywh=532,548,6000,3678",
                    "@type": "sc:Canvas",
                    "label": "[36]",
                    "metadata": [
                        {
                            "label": "Score",
                            "value": 0
                        }
                    ],
                    "thumbnail": "https://iiif.dl.itc.u-tokyo.ac.jp/repo/iiif-img/87922/532,548,6000,3678/,300/0/default.jpg"
                },
                {
                    "@id": "https://iiif.dl.itc.u-tokyo.ac.jp/repo/iiif/dbbf40af-d39e-4339-bb10-2b3ebce97851/canvas/p53#xywh=0,717,7242,3476",
                    "@type": "sc:Canvas",
                    "label": "[37]",
                    "metadata": [
                        {
                            "label": "Score",
                            "value": 0
                        }
                    ],
                    "thumbnail": "https://iiif.dl.itc.u-tokyo.ac.jp/repo/iiif-img/87925/0,717,7242,3476/,300/0/default.jpg"
                },
                {
                    "@id": "https://iiif.dl.itc.u-tokyo.ac.jp/repo/iiif/dbbf40af-d39e-4339-bb10-2b3ebce97851/canvas/p54#xywh=475,483,6638,4097",
                    "@type": "sc:Canvas",
                    "label": "[38]",
                    "metadata": [
                        {
                            "label": "Score",
                            "value": 0
                        }
                    ],
                    "thumbnail": "https://iiif.dl.itc.u-tokyo.ac.jp/repo/iiif-img/87926/475,483,6638,4097/,300/0/default.jpg"
                },
                {
                    "@id": "https://iiif.dl.itc.u-tokyo.ac.jp/repo/iiif/dbbf40af-d39e-4339-bb10-2b3ebce97851/canvas/p55#xywh=0,596,6379,3307",
                    "@type": "sc:Canvas",
                    "label": "[39]",
                    "metadata": [
                        {
                            "label": "Score",
                            "value": 0
                        }
                    ],
                    "thumbnail": "https://iiif.dl.itc.u-tokyo.ac.jp/repo/iiif-img/87927/0,596,6379,3307/,300/0/default.jpg"
                },
                {
                    "@id": "https://iiif.dl.itc.u-tokyo.ac.jp/repo/iiif/dbbf40af-d39e-4339-bb10-2b3ebce97851/canvas/p56#xywh=0,524,7242,3508",
                    "@type": "sc:Canvas",
                    "label": "[40]",
                    "metadata": [
                        {
                            "label": "Score",
                            "value": 0
                        }
                    ],
                    "thumbnail": "https://iiif.dl.itc.u-tokyo.ac.jp/repo/iiif-img/87928/0,524,7242,3508/,300/0/default.jpg"
                },
                {
                    "@id": "https://iiif.dl.itc.u-tokyo.ac.jp/repo/iiif/dbbf40af-d39e-4339-bb10-2b3ebce97851/canvas/p58#xywh=1685,1040,3734,2452",
                    "@type": "sc:Canvas",
                    "label": "[41]",
                    "metadata": [
                        {
                            "label": "Score",
                            "value": 0
                        }
                    ],
                    "thumbnail": "https://iiif.dl.itc.u-tokyo.ac.jp/repo/iiif-img/87930/1685,1040,3734,2452/,300/0/default.jpg"
                },
                {
                    "@id": "https://iiif.dl.itc.u-tokyo.ac.jp/repo/iiif/dbbf40af-d39e-4339-bb10-2b3ebce97851/canvas/p59#xywh=0,572,6564,3645",
                    "@type": "sc:Canvas",
                    "label": "[42]",
                    "metadata": [
                        {
                            "label": "Score",
                            "value": 0
                        }
                    ],
                    "thumbnail": "https://iiif.dl.itc.u-tokyo.ac.jp/repo/iiif-img/87931/0,572,6564,3645/,300/0/default.jpg"
                },
                {
                    "@id": "https://iiif.dl.itc.u-tokyo.ac.jp/repo/iiif/dbbf40af-d39e-4339-bb10-2b3ebce97851/canvas/p65#xywh=846,524,6396,3831",
                    "@type": "sc:Canvas",
                    "label": "[43]",
                    "metadata": [
                        {
                            "label": "Score",
                            "value": 0
                        }
                    ],
                    "thumbnail": "https://iiif.dl.itc.u-tokyo.ac.jp/repo/iiif-img/87937/846,524,6396,3831/,300/0/default.jpg"
                },
                {
                    "@id": "https://iiif.dl.itc.u-tokyo.ac.jp/repo/iiif/dbbf40af-d39e-4339-bb10-2b3ebce97851/canvas/p67#xywh=354,282,6888,4290",
                    "@type": "sc:Canvas",
                    "label": "[44]",
                    "metadata": [
                        {
                            "label": "Score",
                            "value": 0
                        }
                    ],
                    "thumbnail": "https://iiif.dl.itc.u-tokyo.ac.jp/repo/iiif-img/87939/354,282,6888,4290/,300/0/default.jpg"
                },
                {
                    "@id": "https://iiif.dl.itc.u-tokyo.ac.jp/repo/iiif/dbbf40af-d39e-4339-bb10-2b3ebce97851/canvas/p67#xywh=548,1040,3758,2694",
                    "@type": "sc:Canvas",
                    "label": "[45]",
                    "metadata": [
                        {
                            "label": "Score",
                            "value": 0
                        }
                    ],
                    "thumbnail": "https://iiif.dl.itc.u-tokyo.ac.jp/repo/iiif-img/87939/548,1040,3758,2694/,300/0/default.jpg"
                },
                {
                    "@id": "https://iiif.dl.itc.u-tokyo.ac.jp/repo/iiif/dbbf40af-d39e-4339-bb10-2b3ebce97851/canvas/p71#xywh=862,645,6380,3734",
                    "@type": "sc:Canvas",
                    "label": "[46]",
                    "metadata": [
                        {
                            "label": "Score",
                            "value": 0
                        }
                    ],
                    "thumbnail": "https://iiif.dl.itc.u-tokyo.ac.jp/repo/iiif-img/87943/862,645,6380,3734/,300/0/default.jpg"
                },
                {
                    "@id": "https://iiif.dl.itc.u-tokyo.ac.jp/repo/iiif/dbbf40af-d39e-4339-bb10-2b3ebce97851/canvas/p72#xywh=0,733,6484,3484",
                    "@type": "sc:Canvas",
                    "label": "[47]",
                    "metadata": [
                        {
                            "label": "Score",
                            "value": 0
                        }
                    ],
                    "thumbnail": "https://iiif.dl.itc.u-tokyo.ac.jp/repo/iiif-img/87944/0,733,6484,3484/,300/0/default.jpg"
                },
                {
                    "@id": "https://iiif.dl.itc.u-tokyo.ac.jp/repo/iiif/dbbf40af-d39e-4339-bb10-2b3ebce97851/canvas/p73#xywh=403,621,6839,3790",
                    "@type": "sc:Canvas",
                    "label": "[48]",
                    "metadata": [
                        {
                            "label": "Score",
                            "value": 0
                        }
                    ],
                    "thumbnail": "https://iiif.dl.itc.u-tokyo.ac.jp/repo/iiif-img/87945/403,621,6839,3790/,300/0/default.jpg"
                },
                {
                    "@id": "https://iiif.dl.itc.u-tokyo.ac.jp/repo/iiif/dbbf40af-d39e-4339-bb10-2b3ebce97851/canvas/p74#xywh=2467,685,1960,3524",
                    "@type": "sc:Canvas",
                    "label": "[49]",
                    "metadata": [
                        {
                            "label": "Score",
                            "value": 0
                        }
                    ],
                    "thumbnail": "https://iiif.dl.itc.u-tokyo.ac.jp/repo/iiif-img/87946/2467,685,1960,3524/,300/0/default.jpg"
                },
                {
                    "@id": "https://iiif.dl.itc.u-tokyo.ac.jp/repo/iiif/dbbf40af-d39e-4339-bb10-2b3ebce97851/canvas/p75#xywh=32,564,6831,3726",
                    "@type": "sc:Canvas",
                    "label": "[50]",
                    "metadata": [
                        {
                            "label": "Score",
                            "value": 0
                        }
                    ],
                    "thumbnail": "https://iiif.dl.itc.u-tokyo.ac.jp/repo/iiif-img/87947/32,564,6831,3726/,300/0/default.jpg"
                },
                {
                    "@id": "https://iiif.dl.itc.u-tokyo.ac.jp/repo/iiif/dbbf40af-d39e-4339-bb10-2b3ebce97851/canvas/p76#xywh=959,459,6146,3912",
                    "@type": "sc:Canvas",
                    "label": "[51]",
                    "metadata": [
                        {
                            "label": "Score",
                            "value": 0
                        }
                    ],
                    "thumbnail": "https://iiif.dl.itc.u-tokyo.ac.jp/repo/iiif-img/87948/959,459,6146,3912/,300/0/default.jpg"
                },
                {
                    "@id": "https://iiif.dl.itc.u-tokyo.ac.jp/repo/iiif/dbbf40af-d39e-4339-bb10-2b3ebce97851/canvas/p77#xywh=201,645,6146,3355",
                    "@type": "sc:Canvas",
                    "label": "[52]",
                    "metadata": [
                        {
                            "label": "Score",
                            "value": 0
                        }
                    ],
                    "thumbnail": "https://iiif.dl.itc.u-tokyo.ac.jp/repo/iiif-img/87949/201,645,6146,3355/,300/0/default.jpg"
                },
                {
                    "@id": "https://iiif.dl.itc.u-tokyo.ac.jp/repo/iiif/dbbf40af-d39e-4339-bb10-2b3ebce97851/canvas/p78#xywh=96,572,7146,3678",
                    "@type": "sc:Canvas",
                    "label": "[53]",
                    "metadata": [
                        {
                            "label": "Score",
                            "value": 0
                        }
                    ],
                    "thumbnail": "https://iiif.dl.itc.u-tokyo.ac.jp/repo/iiif-img/87950/96,572,7146,3678/,300/0/default.jpg"
                },
                {
                    "@id": "https://iiif.dl.itc.u-tokyo.ac.jp/repo/iiif/dbbf40af-d39e-4339-bb10-2b3ebce97851/canvas/p81#xywh=637,596,6605,3267",
                    "@type": "sc:Canvas",
                    "label": "[54]",
                    "metadata": [
                        {
                            "label": "Score",
                            "value": 0
                        }
                    ],
                    "thumbnail": "https://iiif.dl.itc.u-tokyo.ac.jp/repo/iiif-img/87953/637,596,6605,3267/,300/0/default.jpg"
                },
                {
                    "@id": "https://iiif.dl.itc.u-tokyo.ac.jp/repo/iiif/dbbf40af-d39e-4339-bb10-2b3ebce97851/canvas/p83#xywh=362,524,6356,3758",
                    "@type": "sc:Canvas",
                    "label": "[55]",
                    "metadata": [
                        {
                            "label": "Score",
                            "value": 0
                        }
                    ],
                    "thumbnail": "https://iiif.dl.itc.u-tokyo.ac.jp/repo/iiif-img/87955/362,524,6356,3758/,300/0/default.jpg"
                }
            ],
            "within": {
                "@id": "https://iiif.dl.itc.u-tokyo.ac.jp/repo/iiif/dbbf40af-d39e-4339-bb10-2b3ebce97851/manifest",
                "@type": "sc:Manifest",
                "label": "大正6年衆議院議員立候補(第13回)宮武外骨以外 (推薦書・宣言書等)"
            }
        }
    ]
}