{
    "@context": [
        "http://iiif.io/api/presentation/2/context.json",
        "http://codh.rois.ac.jp/iiif/curation/1/context.json"
    ],
    "@id": "https://nakamura196.github.io/gaikotsu-i/curation/d52be6662453f2b0046649ed90989e94.json",
    "@type": "cr:Curation",
    "label": "Curating list",
    "selections": [
        {
            "@id": "https://nakamura196.github.io/gaikotsu-i/curation/d52be6662453f2b0046649ed90989e94.json/range1",
            "@type": "sc:Range",
            "label": "Manual curation by IIIF Curation Viewer",
            "members": [
                {
                    "@id": "https://iiif.dl.itc.u-tokyo.ac.jp/repo/iiif/30fb8e76-0667-489a-bc88-43c9d8d02513/canvas/p2#xywh=474,0,6099,4912",
                    "@type": "sc:Canvas",
                    "label": "[1]",
                    "metadata": [
                        {
                            "label": "Score",
                            "value": 0
                        }
                    ],
                    "thumbnail": "https://iiif.dl.itc.u-tokyo.ac.jp/repo/iiif-img/86429/474,0,6099,4912/,300/0/default.jpg"
                },
                {
                    "@id": "https://iiif.dl.itc.u-tokyo.ac.jp/repo/iiif/30fb8e76-0667-489a-bc88-43c9d8d02513/canvas/p4#xywh=695,679,6157,4233",
                    "@type": "sc:Canvas",
                    "label": "[2]",
                    "metadata": [
                        {
                            "label": "Score",
                            "value": 0
                        }
                    ],
                    "thumbnail": "https://iiif.dl.itc.u-tokyo.ac.jp/repo/iiif-img/86431/695,679,6157,4233/,300/0/default.jpg"
                },
                {
                    "@id": "https://iiif.dl.itc.u-tokyo.ac.jp/repo/iiif/30fb8e76-0667-489a-bc88-43c9d8d02513/canvas/p5#xywh=368,0,6598,4912",
                    "@type": "sc:Canvas",
                    "label": "[3]",
                    "metadata": [
                        {
                            "label": "Score",
                            "value": 0
                        }
                    ],
                    "thumbnail": "https://iiif.dl.itc.u-tokyo.ac.jp/repo/iiif-img/86432/368,0,6598,4912/,300/0/default.jpg"
                },
                {
                    "@id": "https://iiif.dl.itc.u-tokyo.ac.jp/repo/iiif/30fb8e76-0667-489a-bc88-43c9d8d02513/canvas/p7#xywh=360,605,6639,4307",
                    "@type": "sc:Canvas",
                    "label": "[4]",
                    "metadata": [
                        {
                            "label": "Score",
                            "value": 0
                        }
                    ],
                    "thumbnail": "https://iiif.dl.itc.u-tokyo.ac.jp/repo/iiif-img/86434/360,605,6639,4307/,300/0/default.jpg"
                },
                {
                    "@id": "https://iiif.dl.itc.u-tokyo.ac.jp/repo/iiif/30fb8e76-0667-489a-bc88-43c9d8d02513/canvas/p10#xywh=679,384,5632,4446",
                    "@type": "sc:Canvas",
                    "label": "[5]",
                    "metadata": [
                        {
                            "label": "Score",
                            "value": 0
                        }
                    ],
                    "thumbnail": "https://iiif.dl.itc.u-tokyo.ac.jp/repo/iiif-img/86437/679,384,5632,4446/,300/0/default.jpg"
                },
                {
                    "@id": "https://iiif.dl.itc.u-tokyo.ac.jp/repo/iiif/30fb8e76-0667-489a-bc88-43c9d8d02513/canvas/p11#xywh=957,0,5092,4912",
                    "@type": "sc:Canvas",
                    "label": "[6]",
                    "metadata": [
                        {
                            "label": "Score",
                            "value": 0
                        }
                    ],
                    "thumbnail": "https://iiif.dl.itc.u-tokyo.ac.jp/repo/iiif-img/86438/957,0,5092,4912/,300/0/default.jpg"
                },
                {
                    "@id": "https://iiif.dl.itc.u-tokyo.ac.jp/repo/iiif/30fb8e76-0667-489a-bc88-43c9d8d02513/canvas/p12#xywh=122,0,6738,4298",
                    "@type": "sc:Canvas",
                    "label": "[7]",
                    "metadata": [
                        {
                            "label": "Score",
                            "value": 0
                        }
                    ],
                    "thumbnail": "https://iiif.dl.itc.u-tokyo.ac.jp/repo/iiif-img/86439/122,0,6738,4298/,300/0/default.jpg"
                }
            ],
            "within": {
                "@id": "https://iiif.dl.itc.u-tokyo.ac.jp/repo/iiif/30fb8e76-0667-489a-bc88-43c9d8d02513/manifest",
                "@type": "sc:Manifest",
                "label": "[広告「頓智協会雑誌」](「時事新報」1829号(明治21年2月9日1面))"
            }
        }
    ]
}